[
    {
        "x_coord": 11.354536097702727,
        "y_coord": 55.53905680616001,
        "model": "NTK 500/35",
        "capacity_kw": 550.0,
        "kommune": "Sorø",
        "gsrn": "570714700000005336",
        "connection_date": "1997-07-10",
        "rotor_diameter": 37,
        "hub_height": 35,
        "manufacture": "Nordtank",
        "location_type": "LAND",
        "cadastral_district": "Ruds Vedby By, Ruds Vedby",
        "cadastral_no": "1a",
        "coordinate_origin": "SDFE2018"
    },
    {
        "x_coord": 11.354748310132495,
        "y_coord": 55.54004252339436,
        "model": "NTK 500/35",
        "capacity_kw": 550.0,
        "kommune": "Sorø",
        "gsrn": "570714700000005350",
        "connection_date": "1997-07-01",
        "rotor_diameter": 37,
        "hub_height": 35,
        "manufacture": "Nordtank",
        "location_type": "LAND",
        "cadastral_district": "Ruds Vedby By, Ruds Vedby",
        "cadastral_no": "1a",
        "coordinate_origin": "SDFE2018"
    },
    {
        "x_coord": 11.354939083840845,
        "y_coord": 55.54102739407996,
        "model": "NTK 500/35",
        "capacity_kw": 550.0,
        "kommune": "Sorø",
        "gsrn": "570714700000005381",
        "connection_date": "1997-10-23",
        "rotor_diameter": 37,
        "hub_height": 35,
        "manufacture": "Nordtank",
        "location_type": "LAND",
        "cadastral_district": "Ruds Vedby By, Ruds Vedby",
        "cadastral_no": "1a",
        "coordinate_origin": "SDFE2018"
    },
    {
        "x_coord": 11.355172535544911,
        "y_coord": 55.54212667440494,
        "model": "Ukendt",
        "capacity_kw": 550.0,
        "kommune": "Sorø",
        "gsrn": "570714700000012563",
        "connection_date": "1999-09-29",
        "rotor_diameter": 41,
        "hub_height": 35,
        "manufacture": "Ukendt",
        "location_type": "LAND",
        "cadastral_district": "Ruds Vedby By, Ruds Vedby",
        "cadastral_no": "1a",
        "coordinate_origin": "SDFE2018"
    },
    {
        "x_coord": 11.574383668439006,
        "y_coord": 55.52258399690234,
        "model": "Ukendt",
        "capacity_kw": 11.0,
        "kommune": "Sorø",
        "gsrn": "570715000000084454",
        "connection_date": "2008-08-08",
        "rotor_diameter": 13,
        "hub_height": 18,
        "manufacture": "Ukendt",
        "location_type": "Land",
        "cadastral_district": "N/A",
        "cadastral_no": "N/A",
        "coordinate_origin": "SDFE2018"
    },
    {
        "x_coord": 11.56894758546517,
        "y_coord": 55.528275693000495,
        "model": "SWT 2.3-93",
        "capacity_kw": 2300.0,
        "kommune": "Sorø",
        "gsrn": "571313174000780944",
        "connection_date": "2013-12-17",
        "rotor_diameter": 93,
        "hub_height": 80,
        "manufacture": "SIEMENS",
        "location_type": "LAND",
        "cadastral_district": "Tjørntved by, Stenlille",
        "cadastral_no": "1a",
        "coordinate_origin": "SDFE2018"
    },
    {
        "x_coord": 11.56336877614185,
        "y_coord": 55.52857589547088,
        "model": "SWT 2.3-93",
        "capacity_kw": 2300.0,
        "kommune": "Sorø",
        "gsrn": "571313174000780951",
        "connection_date": "2013-12-16",
        "rotor_diameter": 93,
        "hub_height": 80,
        "manufacture": "SIEMENS",
        "location_type": "LAND",
        "cadastral_district": "Tjørntved by, Stenlille",
        "cadastral_no": "1a",
        "coordinate_origin": "SDFE2018"
    }
]